{
  "parent": "minecraft:recipes/root",
  "criteria": {
    "has_fermented_spider_eye": {
      "conditions": {
        "items": [
          {
            "items": [
              "minecraft:fermented_spider_eye"
            ]
          }
        ]
      },
      "trigger": "minecraft:inventory_changed"
    },
    "has_healing_potion_tank": {
      "conditions": {
        "items": [
          {
            "items": [
              "oresmod:healing_potion_tank"
            ]
          }
        ]
      },
      "trigger": "minecraft:inventory_changed"
    },
    "has_the_recipe": {
      "conditions": {
        "recipe": "minecraft:harming_potion_tank_from_healing_potion_tank"
      },
      "trigger": "minecraft:recipe_unlocked"
    }
  },
  "requirements": [
    [
      "has_the_recipe",
      "has_fermented_spider_eye",
      "has_healing_potion_tank"
    ]
  ],
  "rewards": {
    "recipes": [
      "minecraft:harming_potion_tank_from_healing_potion_tank"
    ]
  }
}